picai_baseline/__init__.py
picai_baseline/__main__.py
picai_baseline/prepare_data.py
picai_baseline/prepare_data_semi_supervised.py
picai_baseline/py.typed
picai_baseline/nnunet/__init__.py
picai_baseline/nnunet/eval.py
picai_baseline/nnunet/nnunet_baseline.py
picai_baseline/nnunet/softmax_export.py
picai_baseline/nnunet/training_docker/__init__.py
picai_baseline/nnunet/training_docker/focal_loss.py
picai_baseline/nnunet/training_docker/io.py
picai_baseline/nnunet/training_docker/nnUNetTrainerV2_Loss_CE_checkpoints.py
picai_baseline/nnunet/training_docker/nnUNetTrainerV2_Loss_FL_and_CE.py
picai_baseline/nnunet/training_docker/nnUNetTrainerV2_focalLoss.py
picai_baseline/nnunet/training_docker/nnunet_wrapper.py
picai_baseline/nnunet/training_docker/run_training.py
picai_baseline/splits/__init__.py
picai_baseline/splits/picai/__init__.py
picai_baseline/splits/picai/__main__.py
picai_baseline/splits/picai/ds-config-train-fold-0.json
picai_baseline/splits/picai/ds-config-train-fold-1.json
picai_baseline/splits/picai/ds-config-train-fold-2.json
picai_baseline/splits/picai/ds-config-train-fold-3.json
picai_baseline/splits/picai/ds-config-train-fold-4.json
picai_baseline/splits/picai/ds-config-valid-fold-0.json
picai_baseline/splits/picai/ds-config-valid-fold-1.json
picai_baseline/splits/picai/ds-config-valid-fold-2.json
picai_baseline/splits/picai/ds-config-valid-fold-3.json
picai_baseline/splits/picai/ds-config-valid-fold-4.json
picai_baseline/splits/picai/splits.json
picai_baseline/splits/picai_debug/__init__.py
picai_baseline/splits/picai_debug/__main__.py
picai_baseline/splits/picai_debug/ds-config-train-fold-0.json
picai_baseline/splits/picai_debug/ds-config-train-fold-1.json
picai_baseline/splits/picai_debug/ds-config-train-fold-2.json
picai_baseline/splits/picai_debug/ds-config-train-fold-3.json
picai_baseline/splits/picai_debug/ds-config-train-fold-4.json
picai_baseline/splits/picai_debug/ds-config-valid-fold-0.json
picai_baseline-0.8.5.dist-info/LICENSE
picai_baseline-0.8.5.dist-info/METADATA
picai_baseline-0.8.5.dist-info/WHEEL
picai_baseline-0.8.5.dist-info/top_level.txt
picai_baseline-0.8.5.dist-info/RECORD
