Metadata-Version: 2.1
Name: picai_baseline
Version: 0.8.5
Summary: PICAI Baselines
Home-page: https://github.com/DIAGNijmegen/picai_baseline
Author: Joeran Bosma
Author-email: Joeran.Bosma@radboudumc.nl
License: Apache 2.0
Project-URL: Bug Tracker, https://github.com/DIAGNijmegen/picai_baseline/issues
Platform: unix
Platform: linux
Platform: osx
Platform: cygwin
Platform: win32
Classifier: Programming Language :: Python :: 3
Classifier: Programming Language :: Python :: 3 :: Only
Classifier: Programming Language :: Python :: 3.6
Classifier: Programming Language :: Python :: 3.7
Classifier: Programming Language :: Python :: 3.8
Classifier: Programming Language :: Python :: 3.9
Requires-Python: >=3.6
License-File: LICENSE
Requires-Dist: numpy
Requires-Dist: tqdm
Requires-Dist: SimpleITK
Requires-Dist: scipy
Requires-Dist: scikit-learn
Requires-Dist: picai-eval >=1.4.1
Requires-Dist: picai-prep >=2.0.1
Provides-Extra: testing
Requires-Dist: pytest >=6.0 ; extra == 'testing'
Requires-Dist: pytest-cov >=2.0 ; extra == 'testing'
Requires-Dist: mypy >=0.910 ; extra == 'testing'
Requires-Dist: flake8 >=3.9 ; extra == 'testing'
Requires-Dist: tox >=3.24 ; extra == 'testing'
